mongo_link/__init__.py
mongo_link/__version__.py
mongo_link/mongo/__init__.py
mongo_link/mongo/exceptions.py
mongo_link/mongo/driver/__init__.py
mongo_link/mongo/driver/driver.py
mongo_link/mongo/indexes/__init__.py
mongo_link/mongo/indexes/mongo_index.py
mongo_link/mongo/model/__init__.py
mongo_link/mongo/model/mongo_embedded_model.py
mongo_link/mongo/model/mongo_model.py
mongo_link/mongo/motor/__init__.py
mongo_link/mongo/motor/motor_driver.py
mongo_link/mongo/motor/motor_repository.py
mongo_link/mongo/repository/__init__.py
mongo_link/mongo/repository/exceptions.py
mongo_link/mongo/repository/repository.py
mongo_link/mongo/repository/repository_decorators.py
mongo_link/utils/__init__.py
mongo_link/utils/singleton.py
tests/__init__.py
tests/conftest.py
tests/functionality/__init__.py
tests/functionality/create_index.py
tests/utils/__init__.py
tests/utils/config.py
mongo_link-1.0.1.dist-info/LICENCE
mongo_link-1.0.1.dist-info/METADATA
mongo_link-1.0.1.dist-info/WHEEL
mongo_link-1.0.1.dist-info/top_level.txt
mongo_link-1.0.1.dist-info/RECORD
