Metadata-Version: 2.1
Name: mongo-link
Version: 1.0.1
Summary: Mongo link is a orm wrapper for motor and pymongo
Home-page: https://github.com/kovtunov-oleksandr/MongoLink
Author: Kovtunov Oleksandr
Author-email: kovtunov.oleksandr.00@gmail.com
Requires-Python: >=3.6
License-File: LICENCE
Requires-Dist: pydantic (==1.10.7)
Requires-Dist: motor (==3.1.2)
